experiment_notebook_widget/__init__.py
experiment_notebook_widget/_version.py
experiment_notebook_widget/callbacks.py
experiment_notebook_widget/widget.py
experiment_notebook_widget/labextension/package.json
experiment_notebook_widget/labextension/static/261.5f5255f0d2a79115033e.js
experiment_notebook_widget/labextension/static/486.8491829518b5e4f7fc44.js
experiment_notebook_widget/labextension/static/486.8491829518b5e4f7fc44.js.LICENSE.txt
experiment_notebook_widget/labextension/static/490.2fe39f2de7fbcd2bce33.js
experiment_notebook_widget/labextension/static/490.2fe39f2de7fbcd2bce33.js.LICENSE.txt
experiment_notebook_widget/labextension/static/568.8938f099199de99a312d.js
experiment_notebook_widget/labextension/static/remoteEntry.5f707419c8551b46b17a.js
experiment_notebook_widget/labextension/static/style.js
experiment_notebook_widget/labextension/static/third-party-licenses.json
experiment_notebook_widget/nbextension/extension.js
experiment_notebook_widget/nbextension/index.js
experiment_notebook_widget/nbextension/index.js.LICENSE.txt
experiment_notebook_widget/tests/__init__.py
experiment_notebook_widget/tests/fix_bug.py
experiment_notebook_widget/tests/run_catboost.py
experiment_notebook_widget/tests/run_distribution.py
experiment_notebook_widget/tests/run_drift.py
experiment_notebook_widget/tests/run_experiment_util.py
experiment_notebook_widget/tests/run_feature_generation.py
experiment_notebook_widget/tests/run_final_train.py
experiment_notebook_widget/tests/run_get_proba_density.py
experiment_notebook_widget/tests/run_lightgbm.py
experiment_notebook_widget/tests/run_linearity.py
experiment_notebook_widget/tests/run_perm_selection.py
experiment_notebook_widget/tests/run_pseudo_label.py
experiment_notebook_widget/tests/run_seaborn.py
experiment_notebook_widget/tests/run_search.py
experiment_notebook_widget/tests/run_selection.py
experiment_notebook_widget/tests/run_xgboost.py
experiment_notebook_widget-0.1.0.dist-info/METADATA
experiment_notebook_widget-0.1.0.dist-info/WHEEL
experiment_notebook_widget-0.1.0.dist-info/top_level.txt
experiment_notebook_widget-0.1.0.dist-info/RECORD
